LICENSE
ProFed/UTKFaceDataset.py
ProFed/__init__.py
ProFed/partitioner.py
profed-0.7.3.dist-info/LICENSE
profed-0.7.3.dist-info/METADATA
profed-0.7.3.dist-info/WHEEL
profed-0.7.3.dist-info/RECORD
