Metadata-Version: 2.1
Name: ProFed
Version: 0.7.3
Summary: A benchmark for proximity-based non-IID Federated Learning
Home-page: https://github.com/davidedomini/ProFed
License: MIT
Author: Davide Domini
Author-email: davide.domini@unibo.it
Requires-Python: >=3.12,<4.0
Classifier: License :: OSI Approved :: MIT License
Classifier: Operating System :: OS Independent
Classifier: Programming Language :: Python :: 3
Classifier: Programming Language :: Python :: 3.12
Classifier: Topic :: Software Development :: Libraries :: Python Modules
Classifier: Topic :: System :: Benchmark
Requires-Dist: datasets (==3.6.0)
Requires-Dist: fsspec (==2025.3.0)
Requires-Dist: numpy (>=2.2.2,<3.0.0)
Requires-Dist: tensorflow-datasets (==4.9.9)
Requires-Dist: torch (>=2.7.0,<3.0.0)
Requires-Dist: torchvision (>=0.22.0,<0.23.0)
Project-URL: Changelog, https://github.com/davidedomini/ProFed/blob/main/CHANGELOG.md
Project-URL: Repository, https://github.com/davidedomini/ProFed
